matrix_semantic_map/OLS_tools.py
matrix_semantic_map/__init__.py
matrix_semantic_map/matrix_map_tools.py
matrix_semantic_map/schema_test_suite.py
matrix_semantic_map/json_schema/expression_matrix_semantic_map.json
matrix_semantic_map/test/__init__.py
matrix_semantic_map/test/testMapBuilder.py
matrix_semantic_map/test/test_OLSQueryWrapper.py
matrix_semantic_map-0.0.8.dist-info/LICENSE
matrix_semantic_map-0.0.8.dist-info/METADATA
matrix_semantic_map-0.0.8.dist-info/WHEEL
matrix_semantic_map-0.0.8.dist-info/top_level.txt
matrix_semantic_map-0.0.8.dist-info/RECORD
