Metadata-Version: 2.1
Name: matrix-semantic-map
Version: 0.0.8
Summary: Semantic mapper for Loom file metadata.
Home-page: https://github.com/HumanCellAtlas/matrix_semantic_map/
Author: David Osumi-Sutherland
Author-email: dosumis@gmail.com
License: UNKNOWN
Project-URL: Bug Reports, https://github.com/HumanCellAtlas/matrix_semantic_map/issues
Project-URL: Source, https://github.com/HumanCellAtlas/matrix_semantic_map/src
Platform: UNKNOWN
Classifier: Development Status :: 4 - Beta
Classifier: Intended Audience :: Science/Research
Classifier: License :: OSI Approved :: Apache Software License
Classifier: Programming Language :: Python :: 3
Requires-Dist: jsonpath-rw
Requires-Dist: loompy
Requires-Dist: pandas
Requires-Dist: jsonschema
Requires-Dist: requests
Requires-Dist: setuptools
